h1st/contrib/pmfp/data_mgmt/__init__.py
h1st/contrib/pmfp/data_mgmt/equipment_parquet_data.py
h1st/contrib/pmfp/models/__init__.py
h1st/contrib/pmfp/models/base.py
h1st/contrib/pmfp/models/oracle/__init__.py
h1st/contrib/pmfp/models/oracle/ensemble/basic.py
h1st/contrib/pmfp/models/oracle/student/timeseries_dl.py
h1st/contrib/pmfp/models/oracle/teacher/base.py
h1st/contrib/pmfp/tools/__init__.py
h1st/contrib/pmfp/tools/oracle/__init__.py
h1st/contrib/pmfp/tools/oracle/build.py
h1st/contrib/pmfp/tools/oracle/exec.py
h1st/contrib/pmfp/tools/oracle/tune.py
h1st/core/__init__.py
h1st/core/context.py
h1st/core/viz.py
h1st/exceptions/__init__.py
h1st/exceptions/exception.py
h1st/h1flow/README.md
h1st/h1flow/__init__.py
h1st/h1flow/h1flow.py
h1st/h1flow/h1step.py
h1st/h1flow/h1step_containable.py
h1st/h1flow/temp_step.py
h1st/h1flow/ui/__init__.py
h1st/h1flow/ui/has_ui.py
h1st/h1flow/ui/has_web_ui.py
h1st/metadata.json
h1st/model/README.md
h1st/model/__init__.py
h1st/model/ml/xgboost/classifier.py
h1st/model/ml/xgboost/regression.py
h1st/model/ml/xgboost/utils.py
h1st/model/model.py
h1st/model/oracle/oracle.py
h1st/model/repository/__init__.py
h1st/model/repository/explorer.py
h1st/model/repository/model_repository.py
h1st/model/repository/storage/base.py
h1st/model/repository/storage/local.py
h1st/model/repository/storage/s3.py
h1st/trust/__init__.py
h1st/trust/auditable.py
h1st/trust/debiasable.py
h1st/trust/decision.py
h1st/trust/describable.py
h1st/trust/describer.py
h1st/trust/enums.py
h1st/trust/explainable.py
h1st/trust/explainer.py
h1st/trust/lime_model_explainer.py
h1st/trust/output_formatters.py
h1st/trust/shap_model_describer.py
h1st/trust/trustable.py
h1st/utils/data_proc/__init__.py
h1st/utils/data_proc/_abstract.py
h1st/utils/data_proc/pandas.py
h1st/utils/data_proc/parquet.py
h1st/utils/data_types/arrow.py
h1st/utils/data_types/numpy_pandas.py
h1st/utils/data_types/python.py
h1st/utils/data_types/spark_sql.py
h1st/utils/debug.py
h1st/utils/default_dict.py
h1st_contrib-2.1.8.dev1.dist-info/LICENSE
h1st_contrib-2.1.8.dev1.dist-info/METADATA
h1st_contrib-2.1.8.dev1.dist-info/WHEEL
h1st_contrib-2.1.8.dev1.dist-info/entry_points.txt
h1st_contrib-2.1.8.dev1.dist-info/RECORD
