Metadata-Version: 2.1
Name: h1st-contrib
Version: 2.1.8.dev1
Summary: Human-First AI (H1st)
Home-page: https://h1st.ai
License: Apache-2.0
Author: Aitomatic, Inc.
Author-email: engineering@aitomatic.com
Requires-Python: >=3.11
Classifier: License :: OSI Approved :: Apache Software License
Classifier: Programming Language :: Python :: 3
Classifier: Programming Language :: Python :: 3.11
Requires-Dist: click (>=8.1.3)
Requires-Dist: fsspec (>=2023.6.0)
Requires-Dist: graphviz (>=0.20.1)
Requires-Dist: imbalanced-learn (>=0.10.1)
Requires-Dist: lime (>=0.2.0.1)
Requires-Dist: loguru (>=0.7.0)
Requires-Dist: numpy (>=1.23)
Requires-Dist: pandas (>=1.5)
Requires-Dist: pyarrow (>=12.0.1)
Requires-Dist: pyspark (>=3.4.1)
Requires-Dist: python-dotenv (>=1.0.0)
Requires-Dist: pyyaml (>=6.0)
Requires-Dist: ruamel.yaml (>=0.17.21)
Requires-Dist: s3fs (>=2023.6.0)
Requires-Dist: scikit-fuzzy (>=0.4.2)
Requires-Dist: scikit-learn (>=1.3.0)
Requires-Dist: shap (>=0.41.0) ; python_version < "3.11"
Requires-Dist: tensorflow (>=2.13.0)
Requires-Dist: tqdm (>=4.65.0)
Requires-Dist: ulid-py (>=1.1.0)
Requires-Dist: xgboost (>=1.7.6)
Project-URL: Repository, https://github.com/h1st-ai/h1st
